mitosheet_helper_config/__init__.py
mitosheet_helper_config/mito_config.py
mitosheet_helper_config/mito_config_utils.py
mitosheet_helper_config-0.0.1.dist-info/METADATA
mitosheet_helper_config-0.0.1.dist-info/WHEEL
mitosheet_helper_config-0.0.1.dist-info/top_level.txt
mitosheet_helper_config-0.0.1.dist-info/RECORD
