Metadata-Version: 2.1
Name: mitosheet-helper-config
Version: 0.0.1
Summary: A configuration package for the mitosheet package, available to enterprise users only
Author-email: Aaron Diamond-Reivich <aarondr77@gmail.com>
Project-URL: Homepage, https://github.com/pypa/sampleproject
Project-URL: Bug Tracker, https://github.com/pypa/sampleproject/issues
Classifier: Programming Language :: Python :: 3
Classifier: Operating System :: OS Independent
Requires-Python: >=3.7
